imessage_exporter/__init__.py
imessage_exporter/cli.py
imessage_exporter/core.py
imessage_exporter/database.py
imessage_exporter/utils.py
imessage_exporter-0.2.0.dist-info/METADATA
imessage_exporter-0.2.0.dist-info/WHEEL
imessage_exporter-0.2.0.dist-info/entry_points.txt
imessage_exporter-0.2.0.dist-info/top_level.txt
imessage_exporter-0.2.0.dist-info/RECORD
