Metadata-Version: 2.4
Name: imessage-exporter
Version: 0.2.0
Summary: A tool to export and search iMessages from local chat.db
Author-email: User <user@example.com>
Classifier: Programming Language :: Python :: 3
Classifier: License :: OSI Approved :: MIT License
Classifier: Operating System :: MacOS
Requires-Python: >=3.7
